stylemapper/__init__.py
stylemapper/stylemapper.py
stylemapper/helpers/__init__.py
stylemapper/helpers/beautify.py
stylemapper/helpers/compare.py
stylemapper/helpers/read_args.py
stylemapper/helpers/set_argparse.py
stylemapper/helpers/usage.py
stylemapper/helpers/validate_paths.py
tests/__init__.py
tests/test_stylemapper.py
stylemapper-1.0.2.dist-info/LICENSE
stylemapper-1.0.2.dist-info/METADATA
stylemapper-1.0.2.dist-info/WHEEL
stylemapper-1.0.2.dist-info/entry_points.txt
stylemapper-1.0.2.dist-info/top_level.txt
stylemapper-1.0.2.dist-info/RECORD
