Metadata-Version: 2.1
Name: stylemapper
Version: 1.0.2
Summary: Provides HTML & CSS information based on keyword arguments and filepaths, including styling, unused classes, and other relevant data.
Author: Josh Hofer
Author-email: <josh@securesap.com>
Project-URL: Source, https://github.com/JoshHofer01/StyleMapper
Keywords: python,css,html,front-end,remove unused css
Classifier: Development Status :: 4 - Beta
Classifier: Intended Audience :: Developers
Classifier: Programming Language :: Python :: 3
Classifier: Natural Language :: English
Classifier: Operating System :: Unix
Classifier: Operating System :: MacOS :: MacOS X
Classifier: Operating System :: Microsoft :: Windows
License-File: LICENSE
Requires-Dist: beautifulsoup4
Requires-Dist: tabulate
